<?xml version="1.0" encoding="UTF-8" standalone="no"?>
<Canvas xmlns="http://www.jgrasp.org">
  <Language>Java</Language>
  <ShowTypes>false</ShowTypes>
  <Version>2</Version>
  <Grid>
    <Snap>true</Snap>
    <Show>false</Show>
  </Grid>
  <Scope id="0">
    <Name>main</Name>
    <Signature>([Ljava/lang/String;)V</Signature>
    <DeclaringType>ConeListMenuApp2</DeclaringType>
    <Depth>0</Depth>
  </Scope>
  <Frame>
    <Bounds>
      <AutoSize>false</AutoSize>
      <X>2</X>
      <Y>170</Y>
      <W>1365</W>
      <H>107</H>
    </Bounds>
    <PanelSize>
      <Key>_X_A_PresentationView0</Key>
      <Order>4</Order>
      <W>1371</W>
      <H>134</H>
    </PanelSize>
    <Viewer>
      <ScopeID>0</ScopeID>
      <Expression>`local Cone[]` coneList</Expression>
      <ViewerClass>_X_A_PresentationView</ViewerClass>
    </Viewer>
  </Frame>
  <Frame>
    <Bounds>
      <AutoSize>true</AutoSize>
      <X>380</X>
      <Y>50</Y>
      <W>193</W>
      <H>449</H>
    </Bounds>
    <Viewer>
      <ScopeID>0</ScopeID>
      <Expression>`local ConeList2` cList.list</Expression>
      <ViewerClass>_X_ElementView</ViewerClass>
    </Viewer>
  </Frame>
  <Frame>
    <Bounds>
      <AutoSize>false</AutoSize>
      <X>50</X>
      <Y>50</Y>
      <W>267</W>
      <H>94</H>
    </Bounds>
    <PanelSize>
      <Key>_X_ElementView0</Key>
      <Order>4</Order>
      <W>273</W>
      <H>121</H>
    </PanelSize>
    <Viewer>
      <ScopeID>0</ScopeID>
      <Expression>`local ConeList2` cList</Expression>
      <ViewerClass>_X_ElementView</ViewerClass>
    </Viewer>
  </Frame>
  <Size>
    <W>697</W>
    <H>371</H>
  </Size>
  <ESize>
    <W>697</W>
    <H>371</H>
  </ESize>
</Canvas>
